roman_numerals/__init__.py
roman_numerals/py.typed
roman_numerals_py-2.0.0.dist-info/WHEEL
roman_numerals_py-2.0.0.dist-info/METADATA
roman_numerals_py-2.0.0.dist-info/RECORD
