Metadata-Version: 2.3
Name: roman-numerals-py
Version: 2.0.0
Summary: Docutils -- Python Documentation Utilities
Author: Adam Turner
Requires-Python: >=3.9
Classifier: Development Status :: 4 - Beta
Classifier: Environment :: Console
Classifier: Intended Audience :: Developers
Classifier: License :: OSI Approved :: Zero-Clause BSD (0BSD)
Classifier: License :: CC0 1.0 Universal (CC0 1.0) Public Domain Dedication
Classifier: Operating System :: OS Independent
Classifier: Programming Language :: Python :: 3
Classifier: Programming Language :: Python :: 3 :: Only
Classifier: Programming Language :: Python :: 3.9
Classifier: Programming Language :: Python :: 3.10
Classifier: Programming Language :: Python :: 3.11
Classifier: Programming Language :: Python :: 3.12
Classifier: Programming Language :: Python :: 3.13
Requires-Dist: mypy ; extra == "lint"
Requires-Dist: ruff ; extra == "lint"
Requires-Dist: pytest ; extra == "test"
Project-URL: Changelog, https://github.com/AA-Turner/roman-numerals/blob/master/CHANGES.rst
Project-URL: Code, https://github.com/AA-Turner/roman-numerals/
Project-URL: Download, https://pypi.org/project/roman-numerals-py/
Project-URL: Issue tracker, https://github.com/AA-Turner/roman-numerals/issues
Provides-Extra: lint
Provides-Extra: test
